DjangoDynamicDrive/__init__.py
DjangoDynamicDrive/db/__init__.py
DjangoDynamicDrive/db/database_router.py
DjangoDynamicDrive/db/db.py
DjangoDynamicDrive/dynamic/__init__.py
DjangoDynamicDrive/dynamic/admin.py
DjangoDynamicDrive/dynamic/apps.py
DjangoDynamicDrive/dynamic/models.py
DjangoDynamicDrive/dynamic/tests.py
DjangoDynamicDrive/dynamic/views.py
DjangoDynamicDrive/dynamic/migrations/__init__.py
djangodynamicdrive-0.0.4.dist-info/METADATA
djangodynamicdrive-0.0.4.dist-info/WHEEL
djangodynamicdrive-0.0.4.dist-info/licenses/LICENSE
djangodynamicdrive-0.0.4.dist-info/RECORD
