Metadata-Version: 2.1
Name: DjangoDynamicDrive
Version: 0.0.4
Summary: Django Rapid Development Assistant Tool
Project-URL: Homepage, https://github.com/xiaoyue9527/DjangoDynamicDrive
Author-email: xiaoyue9527 <xiaoyue9527@hotmail.com>
License: MIT License
License-File: LICENSE
Classifier: License :: OSI Approved :: MIT License
Classifier: Operating System :: OS Independent
Classifier: Programming Language :: Python :: 3
Requires-Python: >=3.7
Requires-Dist: django>=4.0
